pretty_number/__init__.py
pretty_number/_pretty_number.py
pretty_number-0.1.dist-info/LICENSE
pretty_number-0.1.dist-info/METADATA
pretty_number-0.1.dist-info/WHEEL
pretty_number-0.1.dist-info/top_level.txt
pretty_number-0.1.dist-info/RECORD
