Metadata-Version: 2.1
Name: pretty-number
Version: 0.1
Summary: Use unicode to polish python number output.
Home-page: UNKNOWN
Author: szsdk
Author-email: UNKNOWN
License: MIT
Platform: UNKNOWN
